colored_traceback/__init__.py
colored_traceback/__main__.py
colored_traceback/colored_traceback.py
colored_traceback/always/__init__.py
colored_traceback/auto/__init__.py
colored_traceback-0.4.1.dist-info/LICENSE
colored_traceback-0.4.1.dist-info/METADATA
colored_traceback-0.4.1.dist-info/WHEEL
colored_traceback-0.4.1.dist-info/top_level.txt
colored_traceback-0.4.1.dist-info/RECORD
