Metadata-Version: 2.1
Name: colored-traceback
Version: 0.4.1
Summary: Automatically color uncaught exception tracebacks
Home-page: http://www.github.com/staticshock/colored-traceback.py
Author: Anton Backer
Author-email: olegov@gmail.com
License: ISC
Classifier: Development Status :: 4 - Beta
Classifier: Environment :: Console
Classifier: Intended Audience :: Developers
Classifier: Natural Language :: English
Classifier: License :: OSI Approved :: ISC License (ISCL)
Classifier: Operating System :: POSIX :: Linux
Classifier: Operating System :: MacOS :: MacOS X
Classifier: Operating System :: Microsoft :: Windows
Classifier: Programming Language :: Python
Classifier: Programming Language :: Python :: 2.7
Classifier: Programming Language :: Python :: 3.3
License-File: LICENSE
